tests/__init__.py
tests/test_vectorclock.py
vectorclock/__init__.py
vectorclock/vectorclock.py
vectorclock-0.5.3.dist-info/LICENSE
vectorclock-0.5.3.dist-info/METADATA
vectorclock-0.5.3.dist-info/WHEEL
vectorclock-0.5.3.dist-info/top_level.txt
vectorclock-0.5.3.dist-info/RECORD
