Metadata-Version: 2.1
Name: vectorclock
Version: 0.5.3
Summary: A vector clock
Author: boxydog
License: MIT License
Project-URL: Homepage, https://github.com/boxydog/vectorclock
Project-URL: Issues, https://github.com/boxydog/vectorclock/issues
Keywords: vector clock
Classifier: Development Status :: 3 - Alpha
Classifier: Intended Audience :: Developers
Classifier: License :: OSI Approved :: MIT License
Classifier: Operating System :: OS Independent
Classifier: Programming Language :: Python :: 3
Classifier: Programming Language :: Python :: 3.8
Classifier: Programming Language :: Python :: 3.9
Classifier: Programming Language :: Python :: 3.10
Classifier: Programming Language :: Python :: 3.11
Classifier: Programming Language :: Python :: 3.12
Classifier: Topic :: Software Development :: Libraries :: Python Modules
Requires-Python: <4.0,>=3.8
License-File: LICENSE
